pywritesmooth/HandwritingSmoother.py
pywritesmooth/__init__.py
pywritesmooth/Data/DataLoader.py
pywritesmooth/Data/LSTMDataInterface.py
pywritesmooth/Data/Stroke.py
pywritesmooth/Data/StrokeDataModule.py
pywritesmooth/Data/StrokeDataset.py
pywritesmooth/Data/StrokeSet.py
pywritesmooth/Data/__init__.py
pywritesmooth/TrainSmoother/GANTrainer.py
pywritesmooth/TrainSmoother/HandwritingSynthesisModel.py
pywritesmooth/TrainSmoother/LSTMTrainer.py
pywritesmooth/TrainSmoother/TrainerInterface.py
pywritesmooth/TrainSmoother/__init__.py
pywritesmooth/Utility/StrokeHelper.py
pywritesmooth/Utility/__init__.py
pywritesmooth-0.9.2.dist-info/LICENSE
pywritesmooth-0.9.2.dist-info/METADATA
pywritesmooth-0.9.2.dist-info/WHEEL
pywritesmooth-0.9.2.dist-info/entry_points.txt
pywritesmooth-0.9.2.dist-info/top_level.txt
pywritesmooth-0.9.2.dist-info/RECORD
