Metadata-Version: 2.1
Name: pywritesmooth
Version: 0.9.2
Summary: Generate or smooth handwriting
Home-page: https://github.com/EdwardAF-IT/Capstone
Author: Edward Fry
Author-email: edwardaf@outlook.com
License: UNKNOWN
Platform: UNKNOWN
Classifier: Programming Language :: Python :: 3
Classifier: License :: OSI Approved :: MIT License
Classifier: Operating System :: OS Independent
Requires-Python: >=3.7
Requires-Dist: beautifulsoup4
Requires-Dist: click
Requires-Dist: ipython
Requires-Dist: ipywidgets
Requires-Dist: lxml
Requires-Dist: matplotlib
Requires-Dist: numpy
Requires-Dist: Pillow
Requires-Dist: pytorch-lightning
Requires-Dist: scikit-learn
Requires-Dist: scipy
Requires-Dist: svgwrite
Requires-Dist: torch
